{"_default": {"1": {"pseudo": "Shitter Team", "content": "FINAL VERSION 1.0", "date": "2023/06/27 09:31", "likes": 1, "profile_picture": "https://api.dicebear.com/6.x/thumbs/png?seed=Shitter Team", "isReply": false, "id": "58083011"}, "2": {"pseudo": "canard", "content": "Finally! When do we publish it ?", "date": "2023/06/27 09:42", "likes": 0, "profile_picture": "https://api.dicebear.com/6.x/thumbs/png?seed=canard", "isReply": true, "repliedID": "58083011", "id": "42868862"}, "3": {"pseudo": "Bonjour", "content": "Bonjour ", "date": "2023/06/29 17:13", "likes": 0, "profile_picture": "https://api.dicebear.com/6.x/thumbs/png?seed=Bonjour", "isReply": false, "id": "12101854"}, "4": {"pseudo": "ok", "content": "ok", "date": "2023/07/07 16:56", "likes": 0, "profile_picture": "https://api.dicebear.com/6.x/thumbs/png?seed=ok", "isReply": false, "id": "10045785"}, "5": {"pseudo": "ok", "content": "ok", "date": "2023/07/07 17:17", "likes": 0, "profile_picture": "https://api.dicebear.com/6.x/thumbs/png?seed=ok", "isReply": false, "id": "64067237"}, "6": {"pseudo": "ok", "content": "ok", "date": "2023/07/07 17:18", "likes": 0, "profile_picture": "https://api.dicebear.com/6.x/thumbs/png?seed=ok", "isReply": true, "repliedID": "64067237", "id": "19987781"}, "7": {"pseudo": "Anonymous", "content": "Qui a cass\u00e9 shitter ", "date": "2023/07/08 15:42", "likes": 0, "profile_picture": "https://api.dicebear.com/6.x/thumbs/png?seed=Anonymous", "isReply": false, "id": "67427839"}, "8": {"pseudo": "canard", "content": "ah non c'est bon en fait", "date": "2023/07/09 09:10", "likes": 0, "profile_picture": "https://api.dicebear.com/6.x/thumbs/png?seed=canard", "isReply": true, "repliedID": "67427839", "id": "19336718"}, "9": {"pseudo": "Anonymous", "content": "c'est moi", "date": "2023/07/09 16:46", "likes": 0, "profile_picture": "https://api.dicebear.com/6.x/thumbs/png?seed=Anonymous", "isReply": true, "repliedID": "67427839", "id": "16470501"}, "10": {"pseudo": "Shitter Team", "content": "We will eat Twitter, Reddit, Mastodon and Threads ALIVE.\r\n\r\nWe gonna be munchin'", "date": "2023/07/10 22:26", "likes": 0, "profile_picture": "https://api.dicebear.com/6.x/thumbs/png?seed=Shitter Team", "isReply": false, "id": "78581003"}}}